{
    "Rohan": {
        "liked": [
            "E:/videoapp/Videos_Data/video_3.mp4"
        ],
        "disliked": [],
        "comments": {},
        "shares": [
            "video_003",
            "E:/videoapp/Videos_Data/video_1.mp4"
        ]
    },
    "Jhon": {
        "liked": [],
        "disliked": [],
        "comments": {},
        "shares": []
    },
    "Neha": {
        "liked": [],
        "disliked": [],
        "comments": {},
        "shares": []
    },
    "Nikita": {
        "liked": [],
        "disliked": [],
        "comments": {},
        "shares": []
    },
    "Test": {
        "liked": [
            "video_5",
            "video_3"
        ],
        "disliked": [
            "video_2"
        ],
        "comments": {},
        "shares": [],
        "viewed": [
            "video_2",
            "video_5",
            "video_3"
        ]
    },
    "Test1": {
        "liked": [],
        "disliked": [],
        "comments": {},
        "shares": [],
        "viewed": [
            "video_3"
        ]
    },
    "Samm": {
        "liked": [
            "video_2"
        ],
        "disliked": [
            "video_1"
        ],
        "comments": {},
        "shares": [],
        "viewed": [
            "video_2",
            "video_1"
        ]
    },
    "Call": {
        "liked": [
            "video_4"
        ],
        "disliked": [],
        "comments": {
            "video_1": [
                {
                    "comment": "nice",
                    "timestamp": "2024-12-19T10:17:35.792011"
                }
            ]
        },
        "shares": [
            "video_1"
        ],
        "viewed": [
            "video_4",
            "video_2",
            "video_1",
            "video_3"
        ]
    },
    "Yuthika": {
        "liked": [],
        "disliked": [
            "video_3"
        ],
        "comments": {
            "video_3": [
                {
                    "comment": "hi",
                    "timestamp": "2024-12-19T11:41:40.701141"
                }
            ]
        },
        "shares": [],
        "viewed": [
            "video_2",
            "video_1",
            "video_5",
            "video_3",
            "video_6",
            "video_4",
            "video_11",
            "video_15",
            "video_46",
            "video_45"
        ]
    },
    "Dean": {
        "liked": [],
        "disliked": [],
        "comments": {},
        "shares": [],
        "viewed": [
            "video_5",
            "video_2"
        ]
    },
    "Ting": {
        "liked": [],
        "disliked": [
            "video_4"
        ],
        "comments": {
            "video_4": [
                {
                    "comment": "hello",
                    "timestamp": "2024-12-19T13:15:33.366321"
                }
            ]
        },
        "shares": [
            "video_4"
        ],
        "viewed": [
            "video_4",
            "video_2",
            "video_6"
        ]
    },
    "nithish": {
        "liked": [
            "video_46",
            "video_1",
            "video_15",
            "video_46",
            "video_46",
            "video_1",
            "video_15"

        ],
        "disliked": [],
        "comments": {},
        "shares": [],
        "viewed": [
            "video_6",
            "video_45",
            "video_21",
            "video_22",
            "video_24",
            "video_22",
            "video_46",
            "video_1",
            "video_15",
            "video_25",
            "video_24",
            "video_22",
            "video_46",
            "video_22",
            "video_24",
            "video_22",
            "video_46",
            "video_1",
            "video_15"
        ]
    }
}
